owart/__init__.py
owart/cli.py
owart-0.1.0.dist-info/METADATA
owart-0.1.0.dist-info/WHEEL
owart-0.1.0.dist-info/entry_points.txt
owart-0.1.0.dist-info/RECORD
