Metadata-Version: 2.4
Name: owart
Version: 0.1.0
Summary: Poster-style visualizations of neural network weights.
Requires-Python: >=3.13
Requires-Dist: mlx-lm>=0.21.0
Requires-Dist: mlx>=0.30.1
Requires-Dist: numpy>=2.0.0
Requires-Dist: pillow>=11.0.0
Requires-Dist: tqdm>=4.67.1
